nswcovid/__init__.py
nswcovid/exceptions.py
nswcovid/API/__init__.py
nswcovid/API/main.py
nswcovid/address/__init__.py
nswcovid/address/geocode.py
nswcovid/protocol/__init__.py
nswcovid/protocol/protocol.py
nswcovid/protocol/statistics.py
nswcovid/protocol/data_sources/__init__.py
nswcovid/protocol/data_sources/data.json
nswcovid/protocol/event_payload/__init__.py
nswcovid-0.2.2.dist-info/LICENSE
nswcovid-0.2.2.dist-info/METADATA
nswcovid-0.2.2.dist-info/WHEEL
nswcovid-0.2.2.dist-info/top_level.txt
nswcovid-0.2.2.dist-info/RECORD
