Metadata-Version: 2.1
Name: nswcovid
Version: 0.2.2
Summary: Get NSW Covid data from NSW Health
Home-page: https://github.com/troykelly/python-nswcovid
Author: Troy Kelly
Author-email: troy@troykelly.com
License: mit
Project-URL: Documentation, https://github.com/troykelly/python-nswcovid/wiki
Platform: any
Classifier: Development Status :: 4 - Beta
Classifier: Programming Language :: Python
Requires-Dist: backoff
Requires-Dist: requests
Requires-Dist: beautifulsoup4
Requires-Dist: lxml
Requires-Dist: jello
Provides-Extra: testing
Requires-Dist: pytest ; extra == 'testing'
Requires-Dist: pytest-cov ; extra == 'testing'
Requires-Dist: pytest-asyncio ; extra == 'testing'
